{
  "name": "hsv",
  "colors": [
    {
      "r": 1.0,
      "g": 0.0,
      "b": 0.0
    },
    {
      "r": 1.0,
      "g": 0.023162,
      "b": 0.0
    },
    {
      "r": 1.0,
      "g": 0.046324,
      "b": 0.0
    },
    {
      "r": 1.0,
      "g": 0.069485,
      "b": 0.0
    },
    {
      "r": 1.0,
      "g": 0.092647,
      "b": 0.0
    },
    {
      "r": 1.0,
      "g": 0.115809,
      "b": 0.0
    },
    {
      "r": 1.0,
      "g": 0.138971,
      "b": 0.0
    },
    {
      "r": 1.0,
      "g": 0.162133,
      "b": 0.0
    },
    {
      "r": 1.0,
      "g": 0.185294,
      "b": 0.0
    },
    {
      "r": 1.0,
      "g": 0.208456,
      "b": 0.0
    },
    {
      "r": 1.0,
      "g": 0.231618,
      "b": 0.0
    },
    {
      "r": 1.0,
      "g": 0.25478,
      "b": 0.0
    },
    {
      "r": 1.0,
      "g": 0.277941,
      "b": 0.0
    },
    {
      "r": 1.0,
      "g": 0.301103,
      "b": 0.0
    },
    {
      "r": 1.0,
      "g": 0.324265,
      "b": 0.0
    },
    {
      "r": 1.0,
      "g": 0.347427,
      "b": 0.0
    },
    {
      "r": 1.0,
      "g": 0.370589,
      "b": 0.0
    },
    {
      "r": 1.0,
      "g": 0.39375,
      "b": 0.0
    },
    {
      "r": 1.0,
      "g": 0.416912,
      "b": 0.0
    },
    {
      "r": 1.0,
      "g": 0.440074,
      "b": 0.0
    },
    {
      "r": 1.0,
      "g": 0.463236,
      "b": 0.0
    },
    {
      "r": 1.0,
      "g": 0.486398,
      "b": 0.0
    },
    {
      "r": 1.0,
      "g": 0.509559,
      "b": 0.0
    },
    {
      "r": 1.0,
      "g": 0.532721,
      "b": 0.0
    },
    {
      "r": 1.0,
      "g": 0.555883,
      "b": 0.0
    },
    {
      "r": 1.0,
      "g": 0.579045,
      "b": 0.0
    },
    {
      "r": 1.0,
      "g": 0.602206,
      "b": 0.0
    },
    {
      "r": 1.0,
      "g": 0.625368,
      "b": 0.0
    },
    {
      "r": 1.0,
      "g": 0.64853,
      "b": 0.0
    },
    {
      "r": 1.0,
      "g": 0.671692,
      "b": 0.0
    },
    {
      "r": 1.0,
      "g": 0.694854,
      "b": 0.0
    },
    {
      "r": 1.0,
      "g": 0.718015,
      "b": 0.0
    },
    {
      "r": 1.0,
      "g": 0.741177,
      "b": 0.0
    },
    {
      "r": 1.0,
      "g": 0.764339,
      "b": 0.0
    },
    {
      "r": 1.0,
      "g": 0.787501,
      "b": 0.0
    },
    {
      "r": 1.0,
      "g": 0.810663,
      "b": 0.0
    },
    {
      "r": 1.0,
      "g": 0.833824,
      "b": 0.0
    },
    {
      "r": 1.0,
      "g": 0.856986,
      "b": 0.0
    },
    {
      "r": 1.0,
      "g": 0.880148,
      "b": 0.0
    },
    {
      "r": 1.0,
      "g": 0.90331,
      "b": 0.0
    },
    {
      "r": 1.0,
      "g": 0.926472,
      "b": 0.0
    },
    {
      "r": 0.995956,
      "g": 0.945589,
      "b": 0.0
    },
    {
      "r": 0.988235,
      "g": 0.96103,
      "b": 0.0
    },
    {
      "r": 0.980514,
      "g": 0.976471,
      "b": 0.0
    },
    {
      "r": 0.972794,
      "g": 0.991912,
      "b": 0.0
    },
    {
      "r": 0.95772,
      "g": 1.0,
      "b": 0.0
    },
    {
      "r": 0.934558,
      "g": 1.0,
      "b": 0.0
    },
    {
      "r": 0.911396,
      "g": 1.0,
      "b": 0.0
    },
    {
      "r": 0.888234,
      "g": 1.0,
      "b": 0.0
    },
    {
      "r": 0.865072,
      "g": 1.0,
      "b": 0.0
    },
    {
      "r": 0.841911,
      "g": 1.0,
      "b": 0.0
    },
    {
      "r": 0.818749,
      "g": 1.0,
      "b": 0.0
    },
    {
      "r": 0.795587,
      "g": 1.0,
      "b": 0.0
    },
    {
      "r": 0.772425,
      "g": 1.0,
      "b": 0.0
    },
    {
      "r": 0.749263,
      "g": 1.0,
      "b": 0.0
    },
    {
      "r": 0.726102,
      "g": 1.0,
      "b": 0.0
    },
    {
      "r": 0.70294,
      "g": 1.0,
      "b": 0.0
    },
    {
      "r": 0.679778,
      "g": 1.0,
      "b": 0.0
    },
    {
      "r": 0.656616,
      "g": 1.0,
      "b": 0.0
    },
    {
      "r": 0.633455,
      "g": 1.0,
      "b": 0.0
    },
    {
      "r": 0.610293,
      "g": 1.0,
      "b": 0.0
    },
    {
      "r": 0.587131,
      "g": 1.0,
      "b": 0.0
    },
    {
      "r": 0.563969,
      "g": 1.0,
      "b": 0.0
    },
    {
      "r": 0.540807,
      "g": 1.0,
      "b": 0.0
    },
    {
      "r": 0.517646,
      "g": 1.0,
      "b": 0.0
    },
    {
      "r": 0.494484,
      "g": 1.0,
      "b": 0.0
    },
    {
      "r": 0.471322,
      "g": 1.0,
      "b": 0.0
    },
    {
      "r": 0.44816,
      "g": 1.0,
      "b": 0.0
    },
    {
      "r": 0.424998,
      "g": 1.0,
      "b": 0.0
    },
    {
      "r": 0.401837,
      "g": 1.0,
      "b": 0.0
    },
    {
      "r": 0.378675,
      "g": 1.0,
      "b": 0.0
    },
    {
      "r": 0.355513,
      "g": 1.0,
      "b": 0.0
    },
    {
      "r": 0.332351,
      "g": 1.0,
      "b": 0.0
    },
    {
      "r": 0.309189,
      "g": 1.0,
      "b": 0.0
    },
    {
      "r": 0.286028,
      "g": 1.0,
      "b": 0.0
    },
    {
      "r": 0.262866,
      "g": 1.0,
      "b": 0.0
    },
    {
      "r": 0.239704,
      "g": 1.0,
      "b": 0.0
    },
    {
      "r": 0.216542,
      "g": 1.0,
      "b": 0.0
    },
    {
      "r": 0.193381,
      "g": 1.0,
      "b": 0.0
    },
    {
      "r": 0.170219,
      "g": 1.0,
      "b": 0.0
    },
    {
      "r": 0.147057,
      "g": 1.0,
      "b": 0.0
    },
    {
      "r": 0.123895,
      "g": 1.0,
      "b": 0.0
    },
    {
      "r": 0.100733,
      "g": 1.0,
      "b": 0.0
    },
    {
      "r": 0.077572,
      "g": 1.0,
      "b": 0.0
    },
    {
      "r": 0.05441,
      "g": 1.0,
      "b": 0.0
    },
    {
      "r": 0.031249,
      "g": 1.0,
      "b": 1e-06
    },
    {
      "r": 0.023529,
      "g": 1.0,
      "b": 0.015443
    },
    {
      "r": 0.015808,
      "g": 1.0,
      "b": 0.030884
    },
    {
      "r": 0.008088,
      "g": 1.0,
      "b": 0.046325
    },
    {
      "r": 0.000367,
      "g": 1.0,
      "b": 0.061766
    },
    {
      "r": 0.0,
      "g": 1.0,
      "b": 0.084561
    },
    {
      "r": 0.0,
      "g": 1.0,
      "b": 0.107722
    },
    {
      "r": 0.0,
      "g": 1.0,
      "b": 0.130884
    },
    {
      "r": 0.0,
      "g": 1.0,
      "b": 0.154046
    },
    {
      "r": 0.0,
      "g": 1.0,
      "b": 0.177207
    },
    {
      "r": 0.0,
      "g": 1.0,
      "b": 0.200369
    },
    {
      "r": 0.0,
      "g": 1.0,
      "b": 0.223531
    },
    {
      "r": 0.0,
      "g": 1.0,
      "b": 0.246692
    },
    {
      "r": 0.0,
      "g": 1.0,
      "b": 0.269854
    },
    {
      "r": 0.0,
      "g": 1.0,
      "b": 0.293016
    },
    {
      "r": 0.0,
      "g": 1.0,
      "b": 0.316177
    },
    {
      "r": 0.0,
      "g": 1.0,
      "b": 0.339339
    },
    {
      "r": 0.0,
      "g": 1.0,
      "b": 0.3625
    },
    {
      "r": 0.0,
      "g": 1.0,
      "b": 0.385662
    },
    {
      "r": 0.0,
      "g": 1.0,
      "b": 0.408824
    },
    {
      "r": 0.0,
      "g": 1.0,
      "b": 0.431985
    },
    {
      "r": 0.0,
      "g": 1.0,
      "b": 0.455147
    },
    {
      "r": 0.0,
      "g": 1.0,
      "b": 0.478309
    },
    {
      "r": 0.0,
      "g": 1.0,
      "b": 0.50147
    },
    {
      "r": 0.0,
      "g": 1.0,
      "b": 0.524632
    },
    {
      "r": 0.0,
      "g": 1.0,
      "b": 0.547794
    },
    {
      "r": 0.0,
      "g": 1.0,
      "b": 0.570955
    },
    {
      "r": 0.0,
      "g": 1.0,
      "b": 0.594117
    },
    {
      "r": 0.0,
      "g": 1.0,
      "b": 0.617279
    },
    {
      "r": 0.0,
      "g": 1.0,
      "b": 0.64044
    },
    {
      "r": 0.0,
      "g": 1.0,
      "b": 0.663602
    },
    {
      "r": 0.0,
      "g": 1.0,
      "b": 0.686763
    },
    {
      "r": 0.0,
      "g": 1.0,
      "b": 0.709925
    },
    {
      "r": 0.0,
      "g": 1.0,
      "b": 0.733087
    },
    {
      "r": 0.0,
      "g": 1.0,
      "b": 0.756248
    },
    {
      "r": 0.0,
      "g": 1.0,
      "b": 0.77941
    },
    {
      "r": 0.0,
      "g": 1.0,
      "b": 0.802572
    },
    {
      "r": 0.0,
      "g": 1.0,
      "b": 0.825733
    },
    {
      "r": 0.0,
      "g": 1.0,
      "b": 0.848895
    },
    {
      "r": 0.0,
      "g": 1.0,
      "b": 0.872057
    },
    {
      "r": 0.0,
      "g": 1.0,
      "b": 0.895218
    },
    {
      "r": 0.0,
      "g": 1.0,
      "b": 0.91838
    },
    {
      "r": 0.0,
      "g": 1.0,
      "b": 0.941542
    },
    {
      "r": 0.0,
      "g": 1.0,
      "b": 0.964703
    },
    {
      "r": 0.0,
      "g": 1.0,
      "b": 0.987865
    },
    {
      "r": 0.0,
      "g": 0.988973,
      "b": 1.0
    },
    {
      "r": 0.0,
      "g": 0.965812,
      "b": 1.0
    },
    {
      "r": 0.0,
      "g": 0.94265,
      "b": 1.0
    },
    {
      "r": 0.0,
      "g": 0.919488,
      "b": 1.0
    },
    {
      "r": 0.0,
      "g": 0.896326,
      "b": 1.0
    },
    {
      "r": 0.0,
      "g": 0.873165,
      "b": 1.0
    },
    {
      "r": 0.0,
      "g": 0.850003,
      "b": 1.0
    },
    {
      "r": 0.0,
      "g": 0.826841,
      "b": 1.0
    },
    {
      "r": 0.0,
      "g": 0.803679,
      "b": 1.0
    },
    {
      "r": 0.0,
      "g": 0.780517,
      "b": 1.0
    },
    {
      "r": 0.0,
      "g": 0.757356,
      "b": 1.0
    },
    {
      "r": 0.0,
      "g": 0.734194,
      "b": 1.0
    },
    {
      "r": 0.0,
      "g": 0.711032,
      "b": 1.0
    },
    {
      "r": 0.0,
      "g": 0.68787,
      "b": 1.0
    },
    {
      "r": 0.0,
      "g": 0.664708,
      "b": 1.0
    },
    {
      "r": 0.0,
      "g": 0.641547,
      "b": 1.0
    },
    {
      "r": 0.0,
      "g": 0.618385,
      "b": 1.0
    },
    {
      "r": 0.0,
      "g": 0.595223,
      "b": 1.0
    },
    {
      "r": 0.0,
      "g": 0.572061,
      "b": 1.0
    },
    {
      "r": 0.0,
      "g": 0.5489,
      "b": 1.0
    },
    {
      "r": 0.0,
      "g": 0.525738,
      "b": 1.0
    },
    {
      "r": 0.0,
      "g": 0.502576,
      "b": 1.0
    },
    {
      "r": 0.0,
      "g": 0.479414,
      "b": 1.0
    },
    {
      "r": 0.0,
      "g": 0.456252,
      "b": 1.0
    },
    {
      "r": 0.0,
      "g": 0.433091,
      "b": 1.0
    },
    {
      "r": 0.0,
      "g": 0.409929,
      "b": 1.0
    },
    {
      "r": 0.0,
      "g": 0.386767,
      "b": 1.0
    },
    {
      "r": 0.0,
      "g": 0.363605,
      "b": 1.0
    },
    {
      "r": 0.0,
      "g": 0.340443,
      "b": 1.0
    },
    {
      "r": 0.0,
      "g": 0.317282,
      "b": 1.0
    },
    {
      "r": 0.0,
      "g": 0.29412,
      "b": 1.0
    },
    {
      "r": 0.0,
      "g": 0.270958,
      "b": 1.0
    },
    {
      "r": 0.0,
      "g": 0.247796,
      "b": 1.0
    },
    {
      "r": 0.0,
      "g": 0.224634,
      "b": 1.0
    },
    {
      "r": 0.0,
      "g": 0.201473,
      "b": 1.0
    },
    {
      "r": 0.0,
      "g": 0.178311,
      "b": 1.0
    },
    {
      "r": 0.0,
      "g": 0.155149,
      "b": 1.0
    },
    {
      "r": 0.0,
      "g": 0.131987,
      "b": 1.0
    },
    {
      "r": 0.0,
      "g": 0.108826,
      "b": 1.0
    },
    {
      "r": 0.0,
      "g": 0.085664,
      "b": 1.0
    },
    {
      "r": 0.0,
      "g": 0.062502,
      "b": 1.0
    },
    {
      "r": 0.00772,
      "g": 0.04706,
      "b": 1.0
    },
    {
      "r": 0.015441,
      "g": 0.031619,
      "b": 1.0
    },
    {
      "r": 0.023161,
      "g": 0.016178,
      "b": 1.0
    },
    {
      "r": 0.030882,
      "g": 0.000737,
      "b": 1.0
    },
    {
      "r": 0.053307,
      "g": 0.0,
      "b": 1.0
    },
    {
      "r": 0.076469,
      "g": 0.0,
      "b": 1.0
    },
    {
      "r": 0.099631,
      "g": 0.0,
      "b": 1.0
    },
    {
      "r": 0.122792,
      "g": 0.0,
      "b": 1.0
    },
    {
      "r": 0.145954,
      "g": 0.0,
      "b": 1.0
    },
    {
      "r": 0.169116,
      "g": 0.0,
      "b": 1.0
    },
    {
      "r": 0.192278,
      "g": 0.0,
      "b": 1.0
    },
    {
      "r": 0.215439,
      "g": 0.0,
      "b": 1.0
    },
    {
      "r": 0.238601,
      "g": 0.0,
      "b": 1.0
    },
    {
      "r": 0.261763,
      "g": 0.0,
      "b": 1.0
    },
    {
      "r": 0.284925,
      "g": 0.0,
      "b": 1.0
    },
    {
      "r": 0.308087,
      "g": 0.0,
      "b": 1.0
    },
    {
      "r": 0.331248,
      "g": 0.0,
      "b": 1.0
    },
    {
      "r": 0.35441,
      "g": 0.0,
      "b": 1.0
    },
    {
      "r": 0.377572,
      "g": 0.0,
      "b": 1.0
    },
    {
      "r": 0.400734,
      "g": 0.0,
      "b": 1.0
    },
    {
      "r": 0.423896,
      "g": 0.0,
      "b": 1.0
    },
    {
      "r": 0.447057,
      "g": 0.0,
      "b": 1.0
    },
    {
      "r": 0.470219,
      "g": 0.0,
      "b": 1.0
    },
    {
      "r": 0.493381,
      "g": 0.0,
      "b": 1.0
    },
    {
      "r": 0.516543,
      "g": 0.0,
      "b": 1.0
    },
    {
      "r": 0.539705,
      "g": 0.0,
      "b": 1.0
    },
    {
      "r": 0.562866,
      "g": 0.0,
      "b": 1.0
    },
    {
      "r": 0.586028,
      "g": 0.0,
      "b": 1.0
    },
    {
      "r": 0.60919,
      "g": 0.0,
      "b": 1.0
    },
    {
      "r": 0.632352,
      "g": 0.0,
      "b": 1.0
    },
    {
      "r": 0.655513,
      "g": 0.0,
      "b": 1.0
    },
    {
      "r": 0.678675,
      "g": 0.0,
      "b": 1.0
    },
    {
      "r": 0.701837,
      "g": 0.0,
      "b": 1.0
    },
    {
      "r": 0.724999,
      "g": 0.0,
      "b": 1.0
    },
    {
      "r": 0.748161,
      "g": 0.0,
      "b": 1.0
    },
    {
      "r": 0.771322,
      "g": 0.0,
      "b": 1.0
    },
    {
      "r": 0.794484,
      "g": 0.0,
      "b": 1.0
    },
    {
      "r": 0.817646,
      "g": 0.0,
      "b": 1.0
    },
    {
      "r": 0.840808,
      "g": 0.0,
      "b": 1.0
    },
    {
      "r": 0.86397,
      "g": 0.0,
      "b": 1.0
    },
    {
      "r": 0.887131,
      "g": 0.0,
      "b": 1.0
    },
    {
      "r": 0.910293,
      "g": 0.0,
      "b": 1.0
    },
    {
      "r": 0.933455,
      "g": 0.0,
      "b": 1.0
    },
    {
      "r": 0.956617,
      "g": 0.0,
      "b": 1.0
    },
    {
      "r": 0.972426,
      "g": 0.0,
      "b": 0.992648
    },
    {
      "r": 0.980147,
      "g": 0.0,
      "b": 0.977206
    },
    {
      "r": 0.987867,
      "g": 0.0,
      "b": 0.961765
    },
    {
      "r": 0.995588,
      "g": 0.0,
      "b": 0.946324
    },
    {
      "r": 1.0,
      "g": 0.0,
      "b": 0.927574
    },
    {
      "r": 1.0,
      "g": 0.0,
      "b": 0.904413
    },
    {
      "r": 1.0,
      "g": 0.0,
      "b": 0.881251
    },
    {
      "r": 1.0,
      "g": 0.0,
      "b": 0.858089
    },
    {
      "r": 1.0,
      "g": 0.0,
      "b": 0.834927
    },
    {
      "r": 1.0,
      "g": 0.0,
      "b": 0.811765
    },
    {
      "r": 1.0,
      "g": 0.0,
      "b": 0.788604
    },
    {
      "r": 1.0,
      "g": 0.0,
      "b": 0.765442
    },
    {
      "r": 1.0,
      "g": 0.0,
      "b": 0.74228
    },
    {
      "r": 1.0,
      "g": 0.0,
      "b": 0.719118
    },
    {
      "r": 1.0,
      "g": 0.0,
      "b": 0.695956
    },
    {
      "r": 1.0,
      "g": 0.0,
      "b": 0.672795
    },
    {
      "r": 1.0,
      "g": 0.0,
      "b": 0.649633
    },
    {
      "r": 1.0,
      "g": 0.0,
      "b": 0.626471
    },
    {
      "r": 1.0,
      "g": 0.0,
      "b": 0.603309
    },
    {
      "r": 1.0,
      "g": 0.0,
      "b": 0.580148
    },
    {
      "r": 1.0,
      "g": 0.0,
      "b": 0.556986
    },
    {
      "r": 1.0,
      "g": 0.0,
      "b": 0.533824
    },
    {
      "r": 1.0,
      "g": 0.0,
      "b": 0.510662
    },
    {
      "r": 1.0,
      "g": 0.0,
      "b": 0.4875
    },
    {
      "r": 1.0,
      "g": 0.0,
      "b": 0.464339
    },
    {
      "r": 1.0,
      "g": 0.0,
      "b": 0.441177
    },
    {
      "r": 1.0,
      "g": 0.0,
      "b": 0.418015
    },
    {
      "r": 1.0,
      "g": 0.0,
      "b": 0.394853
    },
    {
      "r": 1.0,
      "g": 0.0,
      "b": 0.371691
    },
    {
      "r": 1.0,
      "g": 0.0,
      "b": 0.34853
    },
    {
      "r": 1.0,
      "g": 0.0,
      "b": 0.325368
    },
    {
      "r": 1.0,
      "g": 0.0,
      "b": 0.302206
    },
    {
      "r": 1.0,
      "g": 0.0,
      "b": 0.279044
    },
    {
      "r": 1.0,
      "g": 0.0,
      "b": 0.255883
    },
    {
      "r": 1.0,
      "g": 0.0,
      "b": 0.232721
    },
    {
      "r": 1.0,
      "g": 0.0,
      "b": 0.209559
    },
    {
      "r": 1.0,
      "g": 0.0,
      "b": 0.186397
    },
    {
      "r": 1.0,
      "g": 0.0,
      "b": 0.163235
    },
    {
      "r": 1.0,
      "g": 0.0,
      "b": 0.140074
    },
    {
      "r": 1.0,
      "g": 0.0,
      "b": 0.116912
    },
    {
      "r": 1.0,
      "g": 0.0,
      "b": 0.09375
    }
  ],
  "metadata": {
    "source": "matplotlib",
    "num_points": 256,
    "type": "continuous",
    "category": "cyclic"
  }
}